asldro/__init__.py
asldro/cli.py
asldro/definitions.py
asldro/examples.py
asldro/test_cli.py
asldro/test_examples.py
asldro/containers/__init__.py
asldro/containers/image.py
asldro/containers/test_image.py
asldro/data/__init__.py
asldro/data/affine_test_data.py
asldro/data/asl_bids_validator.json
asldro/data/asl_bids_validator.json.license
asldro/data/filepaths.py
asldro/data/hrgt_icbm_2009a_nls_1.5t.json
asldro/data/hrgt_icbm_2009a_nls_1.5t.nii.gz
asldro/data/hrgt_icbm_2009a_nls_3t.json
asldro/data/hrgt_icbm_2009a_nls_3t.nii.gz
asldro/data/m0scan_bids_validator.json
asldro/data/m0scan_bids_validator.json.license
asldro/data/test_data.py
asldro/data/test_filepaths.py
asldro/filters/__init__.py
asldro/filters/acquire_mri_image_filter.py
asldro/filters/add_complex_noise_filter.py
asldro/filters/add_noise_filter.py
asldro/filters/affine_matrix_filter.py
asldro/filters/append_metadata_filter.py
asldro/filters/basefilter.py
asldro/filters/bids_output_filter.py
asldro/filters/combine_time_series_filter.py
asldro/filters/filter_block.py
asldro/filters/fourier_filter.py
asldro/filters/gkm_filter.py
asldro/filters/ground_truth_loader.py
asldro/filters/invert_image_filter.py
asldro/filters/json_loader.py
asldro/filters/mri_signal_filter.py
asldro/filters/nifti_loader.py
asldro/filters/phase_magnitude_filter.py
asldro/filters/resample_filter.py
asldro/filters/scale_offset_filter.py
asldro/filters/test_acquire_mri_image_filter.py
asldro/filters/test_add_complex_noise_filter.py
asldro/filters/test_add_noise_filter.py
asldro/filters/test_affine_matrix_filter.py
asldro/filters/test_append_metadata_filter.py
asldro/filters/test_basefilter.py
asldro/filters/test_bids_output_filter.py
asldro/filters/test_combine_time_series_filter.py
asldro/filters/test_fourier_filter.py
asldro/filters/test_gkm_filter.py
asldro/filters/test_ground_truth_loader.py
asldro/filters/test_invert_image_filter.py
asldro/filters/test_json_loader.py
asldro/filters/test_mri_signal_filter.py
asldro-2.2.0.dist-info/LICENSE
asldro-2.2.0.dist-info/METADATA
asldro-2.2.0.dist-info/WHEEL
asldro-2.2.0.dist-info/entry_points.txt
asldro-2.2.0.dist-info/top_level.txt
asldro-2.2.0.dist-info/RECORD
