Metadata-Version: 2.1
Name: asldro
Version: 2.2.0
Summary: ASL Digital Reference Object
Home-page: https://github.com/gold-standard-phantoms/asldro
Author: Gold Standard Phantoms
Author-email: info@goldstandardphantoms.com
License: MIT
Project-URL: Documentation, https://asldro.readthedocs.io/
Project-URL: Code, https://github.com/gold-standard-phantoms/asldro
Project-URL: Issue tracker, https://github.com/gold-standard-phantoms/asldro/issues
Platform: UNKNOWN
Classifier: Development Status :: 5 - Production/Stable
Classifier: Intended Audience :: Science/Research
Classifier: Topic :: Scientific/Engineering
Classifier: Programming Language :: Python :: 3
Classifier: License :: OSI Approved :: MIT License
Classifier: Operating System :: OS Independent
Requires-Python: >=3.7
Requires-Dist: nibabel (==3.1.1)
Requires-Dist: numpy (==1.19.0)
Requires-Dist: jsonschema (==3.2.0)
Requires-Dist: nilearn (==0.6.2)
